odoo9_addon_website_sale_b2c-9.0.1.0.0-py2.7-nspkg.pth
odoo9_addon_website_sale_b2c-9.0.1.0.0.dist-info/DESCRIPTION.rst
odoo9_addon_website_sale_b2c-9.0.1.0.0.dist-info/METADATA
odoo9_addon_website_sale_b2c-9.0.1.0.0.dist-info/RECORD
odoo9_addon_website_sale_b2c-9.0.1.0.0.dist-info/WHEEL
odoo9_addon_website_sale_b2c-9.0.1.0.0.dist-info/metadata.json
odoo9_addon_website_sale_b2c-9.0.1.0.0.dist-info/namespace_packages.txt
odoo9_addon_website_sale_b2c-9.0.1.0.0.dist-info/top_level.txt
odoo_addons/website_sale_b2c/README.rst
odoo_addons/website_sale_b2c/__init__.py
odoo_addons/website_sale_b2c/__openerp__.py
odoo_addons/website_sale_b2c/controllers/__init__.py
odoo_addons/website_sale_b2c/controllers/main.py
odoo_addons/website_sale_b2c/models/__init__.py
odoo_addons/website_sale_b2c/models/product_pricelist.py
odoo_addons/website_sale_b2c/models/product_product.py
odoo_addons/website_sale_b2c/models/product_template.py
odoo_addons/website_sale_b2c/models/sale_order_line.py
odoo_addons/website_sale_b2c/security/groups.xml
odoo_addons/website_sale_b2c/security/ir.model.access.csv
odoo_addons/website_sale_b2c/static/description/icon.png
odoo_addons/website_sale_b2c/templates/website_sale.xml
odoo_addons/website_sale_b2c/tests/__init__.py
odoo_addons/website_sale_b2c/tests/test_b2c.py
odoo_addons/website_sale_b2c/wizards/__init__.py
odoo_addons/website_sale_b2c/wizards/sale_config_settings.py
odoo_addons/website_sale_b2c/wizards/sale_config_settings.xml
